galileo_core/__init__.py
galileo_core/constants/__init__.py
galileo_core/constants/config.py
galileo_core/constants/dataset_format.py
galileo_core/constants/http_headers.py
galileo_core/constants/job.py
galileo_core/constants/processing_headers.py
galileo_core/constants/request_method.py
galileo_core/constants/routes.py
galileo_core/constants/scorers.py
galileo_core/exceptions/__init__.py
galileo_core/exceptions/base.py
galileo_core/exceptions/execution.py
galileo_core/exceptions/http.py
galileo_core/helpers/__init__.py
galileo_core/helpers/api_client.py
galileo_core/helpers/api_key.py
galileo_core/helpers/dataset.py
galileo_core/helpers/dependencies.py
galileo_core/helpers/event_loop_thread_pool.py
galileo_core/helpers/execution.py
galileo_core/helpers/group.py
galileo_core/helpers/group_integration.py
galileo_core/helpers/group_project.py
galileo_core/helpers/health.py
galileo_core/helpers/integration.py
galileo_core/helpers/logger.py
galileo_core/helpers/metric_critique.py
galileo_core/helpers/pagination.py
galileo_core/helpers/project.py
galileo_core/helpers/scorers.py
galileo_core/helpers/ssl_context.py
galileo_core/helpers/user.py
galileo_core/helpers/user_integration.py
galileo_core/helpers/user_project.py
galileo_core/py.typed
galileo_core/schemas/__init__.py
galileo_core/schemas/base_config.py
galileo_core/schemas/core/__init__.py
galileo_core/schemas/core/api_key.py
galileo_core/schemas/core/auth_method.py
galileo_core/schemas/core/collaboration_role.py
galileo_core/schemas/core/collaborator.py
galileo_core/schemas/core/dataset.py
galileo_core/schemas/core/group.py
galileo_core/schemas/core/group_project.py
galileo_core/schemas/core/group_role.py
galileo_core/schemas/core/group_visibility.py
galileo_core/schemas/core/integration/__init__.py
galileo_core/schemas/core/integration/anthropic.py
galileo_core/schemas/core/integration/anthropic_auth_type.py
galileo_core/schemas/core/integration/aws.py
galileo_core/schemas/core/integration/aws_bedrock.py
galileo_core-3.82.1.dist-info/LICENSE
galileo_core-3.82.1.dist-info/METADATA
galileo_core-3.82.1.dist-info/WHEEL
galileo_core-3.82.1.dist-info/entry_points.txt
galileo_core-3.82.1.dist-info/RECORD
