Metadata-Version: 2.3
Name: galileo-core
Version: 3.82.1
Summary: Shared schemas and configuration for Galileo's Python packages.
License: Apache-2.0
Keywords: llm,quality,language_models,galileo
Author: Galileo Technologies Inc.
Author-email: team@rungalileo.io
Requires-Python: >=3.10.0
Classifier: Development Status :: 5 - Production/Stable
Classifier: Framework :: Pydantic
Classifier: License :: OSI Approved :: Apache Software License
Classifier: Framework :: IPython
Classifier: Framework :: Jupyter
Classifier: Framework :: Jupyter :: JupyterLab
Classifier: Intended Audience :: Developers
Classifier: Intended Audience :: Information Technology
Classifier: Intended Audience :: Science/Research
Classifier: Operating System :: OS Independent
Classifier: Programming Language :: ML
Classifier: Programming Language :: Python :: 3 :: Only
Classifier: Programming Language :: Python :: 3.10
Classifier: Programming Language :: Python :: 3.11
Classifier: Programming Language :: Python :: 3.12
Classifier: Programming Language :: Python :: 3.13
Classifier: Programming Language :: Python :: 3.14
Classifier: Topic :: Scientific/Engineering :: Artificial Intelligence
Classifier: Topic :: Software Development :: Libraries
Classifier: Topic :: Software Development :: Libraries :: Python Modules
Classifier: Typing :: Typed
Provides-Extra: testing
Requires-Dist: httpx (>=0.27.0,<0.29.0)
Requires-Dist: pydantic (>=2.6.0,<3.0.0)
Requires-Dist: pydantic-partial (>=0.10.1,<0.11.0)
Requires-Dist: pydantic-settings (>=2.2.1,<3.0.0)
Requires-Dist: pyjwt (>=2.8.0,<3.0.0)
Requires-Dist: pytest (>=8.2.1,<9.0.0) ; extra == "testing"
Requires-Dist: respx (>=0.22.0,<0.23.0) ; extra == "testing"
Requires-Dist: typing-extensions (>=4.12.2,<5.0.0)
Requires-Dist: uvloop (>=0.21.0,<0.22.0) ; sys_platform != "win32"
Project-URL: Homepage, https://www.galileo.ai/
